[{"firstChar":"L","id":1,"name":"联想"},{"firstChar":"H","id":2,"name":"华为"},{"firstChar":"S","id":3,"name":"三星"},{"firstChar":"X","id":4,"name":"小米"},{"firstChar":"O","id":5,"name":"OPPO"},{"firstChar":"S","id":6,"name":"360"},{"firstChar":"Z","id":7,"name":"中兴"},{"firstChar":"M","id":8,"name":"魅族"},{"firstChar":"P","id":9,"name":"苹果"},{"firstChar":"V","id":10,"name":"VIVO"},{"firstChar":"N","id":11,"name":"诺基亚"},{"firstChar":"C","id":12,"name":"锤子"},{"firstChar":"C","id":13,"name":"长虹"},{"firstChar":"H","id":14,"name":"海尔"},{"firstChar":"F","id":15,"name":"飞利浦"},{"firstChar":"T","id":16,"name":"TCL"},{"firstChar":"H","id":17,"name":"海信"},{"firstChar":"X","id":18,"name":"夏普"},{"firstChar":"C","id":19,"name":"创维"},{"firstChar":"D","id":20,"name":"东芝"},{"firstChar":"K","id":21,"name":"康佳"},{"firstChar":"L","id":22,"name":"LG"}]